{"_id":{"$oid":"5c655362635b7a0cb29783ff"},"node":"production","typeName":"Int","property":"baseIterations","value":"1000000"}
{"_id":{"$oid":"5c655362635b7a0cb2978401"},"node":"production","typeName":"Float","property":"baseIterationsCoefficient","value":"1.0"}
{"_id":{"$oid":"5c655362635b7a0cb2978403"},"node":"production","typeName":"Int","property":"priorityClient","value":"1"}
{"_id":{"$oid":"5c655362635b7a0cb2978405"},"node":"production","typeName":"Int","property":"priorityEmployees","value":"1"}
{"_id":{"$oid":"5c655362635b7a0cb2978407"},"node":"production","typeName":"Int","property":"priorityPurchasing","value":"1"}
{"_id":{"$oid":"5c655362635b7a0cb2978409"},"node":"production","typeName":"Int","property":"priorityProduction","value":"1"}
{"_id":{"$oid":"5c655362635b7a0cb297840b"},"node":"production","typeName":"Int","property":"priorityPublic","value":"1"}
{"_id":{"$oid":"5c655362635b7a0cb297840d"},"node":"production","typeName":"Boolean","property":"mongoTransferRecords","value":"true"}
{"_id":{"$oid":"5c655362635b7a0cb297840f"},"node":"production","typeName":"Boolean","property":"doWarmup","value":"true"}
{"_id":{"$oid":"5c655362635b7a0cb2978411"},"node":"production","typeName":"Boolean","property":"dbBackpressure","value":"true"}
{"_id":{"$oid":"5c655362635b7a0cb2978413"},"node":"production","typeName":"Boolean","property":"debugMode","value":"false"}
{"_id":{"$oid":"5c655362635b7a0cb2978415"},"node":"production","typeName":"Int","property":"groundIterations","value":"1000000"}
{"_id":{"$oid":"5c655362635b7a0cb2978417"},"node":"production","typeName":"Int","property":"cores","value":"2"}
{"_id":{"$oid":"5c655362635b7a0cb2978419"},"node":"production","typeName":"Long","property":"memory","value":"3685744640"}
{"_id":{"$oid":"5c655362635b7a0cb297841b"},"node":"production","typeName":"Int","property":"latencyRecordingInterval","value":"1000"}
{"_id":{"$oid":"5c655362635b7a0cb297841d"},"node":"production","typeName":"Int","property":"performanceRecordingIntervalMs","value":"100"}
{"_id":{"$oid":"5c655362635b7a0cb297841f"},"node":"production","typeName":"Int","property":"throughputRecordingIntervalMs","value":"100"}
{"_id":{"$oid":"5c655362635b7a0cb2978421"},"node":"production","typeName":"Long","property":"waitForBeingColdTimeoutMs","value":"30000"}
{"_id":{"$oid":"5c655362635b7a0cb2978423"},"node":"production","typeName":"Long","property":"waitForBeingColdIntervalMs","value":"5000"}
{"_id":{"$oid":"5c655362635b7a0cb2978425"},"node":"production","typeName":"Boolean","property":"skipExecution","value":"false"}
{"_id":{"$oid":"5c655362635b7a0cb2978427"},"node":"production","typeName":"Boolean","property":"invokeBeforeAllAndAfterAllEvenIfNoTestsAreExpected","value":"false"}
{"_id":{"$oid":"5c655363635b7a0cb297941d"},"node":"client","typeName":"JSON","property":"placement","value":"{\"cost\":138.8982630933588,\"solutions\":[{\"placements\":[{\"operator\":0,\"host\":4},{\"operator\":1,\"host\":4},{\"operator\":2,\"host\":4},{\"operator\":3,\"host\":4},{\"operator\":4,\"host\":4},{\"operator\":5,\"host\":4},{\"operator\":6,\"host\":4},{\"operator\":7,\"host\":4},{\"operator\":8,\"host\":3},{\"operator\":9,\"host\":3},{\"operator\":10,\"host\":3},{\"operator\":11,\"host\":0},{\"operator\":12,\"host\":0},{\"operator\":13,\"host\":0}]}],\"selectedSolution\":0,\"operators\":[{\"id\":0,\"operatorName\":\"actor\",\"hostCandidates\":[0,1,2,3,4],\"selectivity\":1.0,\"load\":0.0,\"outgoingLink\":1000.0},{\"id\":1,\"operatorName\":\"re-classification\",\"hostCandidates\":[0,4],\"selectivity\":1.0,\"load\":0.0,\"outgoingLink\":1000.0},{\"id\":2,\"operatorName\":\"selection\",\"hostCandidates\":[0,4],\"selectivity\":1.0,\"load\":1000.0,\"outgoingLink\":1000.0},{\"id\":3,\"operatorName\":\"actor\",\"hostCandidates\":[0,1,2,3,4],\"selectivity\":1.0,\"load\":0.0,\"outgoingLink\":1000.0},{\"id\":4,\"operatorName\":\"re-classification\",\"hostCandidates\":[0,4],\"selectivity\":1.0,\"load\":0.0,\"outgoingLink\":1000.0},{\"id\":5,\"operatorName\":\"equi-join\",\"hostCandidates\":[0,4],\"selectivity\":0.6000000238418579,\"load\":5200.000047683716,\"outgoingLink\":1200.0000476837158},{\"id\":6,\"operatorName\":\"projection\",\"hostCandidates\":[0,4],\"selectivity\":1.0,\"load\":1200.0000476837158,\"outgoingLink\":1200.0000476837158},{\"id\":7,\"operatorName\":\"duplicate-elimination\",\"hostCandidates\":[0,4],\"selectivity\":0.6666666865348816,\"load\":2400.0000953674316,\"outgoingLink\":800.0000556310027},{\"id\":8,\"operatorName\":\"actor\",\"hostCandidates\":[0,1,2,3,4],\"selectivity\":1.0,\"load\":0.0,\"outgoingLink\":1000.0},{\"id\":9,\"operatorName\":\"re-classification\",\"hostCandidates\":[0,1,2,3,4],\"selectivity\":1.0,\"load\":0.0,\"outgoingLink\":1000.0},{\"id\":10,\"operatorName\":\"duplicate-elimination\",\"hostCandidates\":[0,1,2,3,4],\"selectivity\":1.0,\"load\":2000.0,\"outgoingLink\":1000.0},{\"id\":11,\"operatorName\":\"equi-join\",\"hostCandidates\":[0,4],\"selectivity\":0.5,\"load\":4500.000139077507,\"outgoingLink\":900.0000278155014},{\"id\":12,\"operatorName\":\"projection\",\"hostCandidates\":[0,4],\"selectivity\":1.0,\"load\":900.0000278155014,\"outgoingLink\":900.0000278155014},{\"id\":13,\"operatorName\":\"root\",\"hostCandidates\":[0,4],\"selectivity\":1.0,\"load\":0.0,\"outgoingLink\":900.0000278155014}],\"links\":[{\"sender\":0,\"receiver\":1,\"load\":1000.0},{\"sender\":1,\"receiver\":2,\"load\":1000.0},{\"sender\":3,\"receiver\":4,\"load\":1000.0},{\"sender\":2,\"receiver\":5,\"load\":1000.0},{\"sender\":4,\"receiver\":5,\"load\":1000.0},{\"sender\":5,\"receiver\":6,\"load\":1200.0000476837158},{\"sender\":6,\"receiver\":7,\"load\":1200.0000476837158},{\"sender\":8,\"receiver\":9,\"load\":1000.0},{\"sender\":9,\"receiver\":10,\"load\":1000.0},{\"sender\":7,\"receiver\":11,\"load\":800.0000556310027},{\"sender\":10,\"receiver\":11,\"load\":1000.0},{\"sender\":11,\"receiver\":12,\"load\":900.0000278155014},{\"sender\":12,\"receiver\":13,\"load\":900.0000278155014}],\"hosts\":[{\"id\":0,\"name\":\"clients-host\"},{\"id\":1,\"name\":\"employees-host\"},{\"id\":2,\"name\":\"purchasing-host\"},{\"id\":3,\"name\":\"public-host\"},{\"id\":4,\"name\":\"production-host\"}],\"duration\":207,\"timedOut\":false}"}
{"_id":{"$oid":"5c655363635b7a0cb297942d"},"node":"client","typeName":"Int","property":"baseIterations","value":"1000000"}
{"_id":{"$oid":"5c655363635b7a0cb2979439"},"node":"client","typeName":"Float","property":"baseIterationsCoefficient","value":"1.0"}
{"_id":{"$oid":"5c655363635b7a0cb297943f"},"node":"client","typeName":"Int","property":"priorityClient","value":"1"}
{"_id":{"$oid":"5c655363635b7a0cb2979447"},"node":"client","typeName":"Int","property":"priorityEmployees","value":"1"}
{"_id":{"$oid":"5c655363635b7a0cb297944d"},"node":"client","typeName":"Int","property":"priorityPurchasing","value":"1"}
{"_id":{"$oid":"5c655363635b7a0cb297948d"},"node":"client","typeName":"Int","property":"priorityProduction","value":"1"}
{"_id":{"$oid":"5c655363635b7a0cb2979493"},"node":"client","typeName":"Int","property":"priorityPublic","value":"1"}
{"_id":{"$oid":"5c655363635b7a0cb2979499"},"node":"client","typeName":"Boolean","property":"mongoTransferRecords","value":"true"}
{"_id":{"$oid":"5c655363635b7a0cb29794a1"},"node":"client","typeName":"Boolean","property":"doWarmup","value":"true"}
{"_id":{"$oid":"5c655363635b7a0cb29794a7"},"node":"client","typeName":"Boolean","property":"dbBackpressure","value":"true"}
{"_id":{"$oid":"5c655363635b7a0cb29794ab"},"node":"client","typeName":"Boolean","property":"debugMode","value":"false"}
{"_id":{"$oid":"5c655363635b7a0cb29794b1"},"node":"client","typeName":"Int","property":"groundIterations","value":"1000000"}
{"_id":{"$oid":"5c655363635b7a0cb29794b7"},"node":"client","typeName":"Int","property":"cores","value":"2"}
{"_id":{"$oid":"5c655363635b7a0cb29794bd"},"node":"client","typeName":"Long","property":"memory","value":"3817865216"}
{"_id":{"$oid":"5c655363635b7a0cb29794c3"},"node":"client","typeName":"Int","property":"latencyRecordingInterval","value":"1000"}
{"_id":{"$oid":"5c655363635b7a0cb29794c9"},"node":"client","typeName":"Int","property":"performanceRecordingIntervalMs","value":"100"}
{"_id":{"$oid":"5c655363635b7a0cb29794cf"},"node":"client","typeName":"Int","property":"throughputRecordingIntervalMs","value":"100"}
{"_id":{"$oid":"5c655363635b7a0cb29794d5"},"node":"client","typeName":"Long","property":"waitForBeingColdTimeoutMs","value":"30000"}
{"_id":{"$oid":"5c655363635b7a0cb29794db"},"node":"client","typeName":"Long","property":"waitForBeingColdIntervalMs","value":"5000"}
{"_id":{"$oid":"5c655363635b7a0cb29794e1"},"node":"client","typeName":"Boolean","property":"skipExecution","value":"false"}
{"_id":{"$oid":"5c655363635b7a0cb29794e7"},"node":"client","typeName":"Boolean","property":"invokeBeforeAllAndAfterAllEvenIfNoTestsAreExpected","value":"false"}
{"_id":{"$oid":"5c655363635b7a0cb297afcf"},"node":"employees","typeName":"Int","property":"baseIterations","value":"1000000"}
{"_id":{"$oid":"5c655363635b7a0cb297afdd"},"node":"employees","typeName":"Float","property":"baseIterationsCoefficient","value":"1.0"}
{"_id":{"$oid":"5c655363635b7a0cb297afe7"},"node":"employees","typeName":"Int","property":"priorityClient","value":"1"}
{"_id":{"$oid":"5c655363635b7a0cb297aff3"},"node":"employees","typeName":"Int","property":"priorityEmployees","value":"1"}
{"_id":{"$oid":"5c655363635b7a0cb297affb"},"node":"employees","typeName":"Int","property":"priorityPurchasing","value":"1"}
{"_id":{"$oid":"5c655363635b7a0cb297b005"},"node":"employees","typeName":"Int","property":"priorityProduction","value":"1"}
{"_id":{"$oid":"5c655363635b7a0cb297b00d"},"node":"employees","typeName":"Int","property":"priorityPublic","value":"1"}
{"_id":{"$oid":"5c655363635b7a0cb297b019"},"node":"employees","typeName":"Boolean","property":"mongoTransferRecords","value":"true"}
{"_id":{"$oid":"5c655363635b7a0cb297b029"},"node":"employees","typeName":"Boolean","property":"doWarmup","value":"true"}
{"_id":{"$oid":"5c655363635b7a0cb297b031"},"node":"employees","typeName":"Boolean","property":"dbBackpressure","value":"true"}
{"_id":{"$oid":"5c655363635b7a0cb297b03d"},"node":"employees","typeName":"Boolean","property":"debugMode","value":"false"}
{"_id":{"$oid":"5c655363635b7a0cb297b045"},"node":"employees","typeName":"Int","property":"groundIterations","value":"1000000"}
{"_id":{"$oid":"5c655363635b7a0cb297b04d"},"node":"employees","typeName":"Int","property":"cores","value":"2"}
{"_id":{"$oid":"5c655363635b7a0cb297b055"},"node":"employees","typeName":"Long","property":"memory","value":"3817865216"}
{"_id":{"$oid":"5c655363635b7a0cb297b05f"},"node":"employees","typeName":"Int","property":"latencyRecordingInterval","value":"1000"}
{"_id":{"$oid":"5c655363635b7a0cb297b067"},"node":"employees","typeName":"Int","property":"performanceRecordingIntervalMs","value":"100"}
{"_id":{"$oid":"5c655363635b7a0cb297b071"},"node":"employees","typeName":"Int","property":"throughputRecordingIntervalMs","value":"100"}
{"_id":{"$oid":"5c655363635b7a0cb297b07b"},"node":"employees","typeName":"Long","property":"waitForBeingColdTimeoutMs","value":"30000"}
{"_id":{"$oid":"5c655363635b7a0cb297b085"},"node":"employees","typeName":"Long","property":"waitForBeingColdIntervalMs","value":"5000"}
{"_id":{"$oid":"5c655363635b7a0cb297b08d"},"node":"employees","typeName":"Boolean","property":"skipExecution","value":"false"}
{"_id":{"$oid":"5c655363635b7a0cb297b0a3"},"node":"employees","typeName":"Boolean","property":"invokeBeforeAllAndAfterAllEvenIfNoTestsAreExpected","value":"false"}
{"_id":{"$oid":"5c655364635b7a0cb297b705"},"node":"public","typeName":"Int","property":"baseIterations","value":"1000000"}
{"_id":{"$oid":"5c655364635b7a0cb297b717"},"node":"public","typeName":"Float","property":"baseIterationsCoefficient","value":"1.0"}
{"_id":{"$oid":"5c655364635b7a0cb297b723"},"node":"public","typeName":"Int","property":"priorityClient","value":"1"}
{"_id":{"$oid":"5c655364635b7a0cb297b72b"},"node":"public","typeName":"Int","property":"priorityEmployees","value":"1"}
{"_id":{"$oid":"5c655364635b7a0cb297b735"},"node":"public","typeName":"Int","property":"priorityPurchasing","value":"1"}
{"_id":{"$oid":"5c655364635b7a0cb297b741"},"node":"public","typeName":"Int","property":"priorityProduction","value":"1"}
{"_id":{"$oid":"5c655364635b7a0cb297b74b"},"node":"public","typeName":"Int","property":"priorityPublic","value":"1"}
{"_id":{"$oid":"5c655364635b7a0cb297b757"},"node":"public","typeName":"Boolean","property":"mongoTransferRecords","value":"true"}
{"_id":{"$oid":"5c655364635b7a0cb297b75f"},"node":"public","typeName":"Boolean","property":"doWarmup","value":"true"}
{"_id":{"$oid":"5c655364635b7a0cb297b767"},"node":"public","typeName":"Boolean","property":"dbBackpressure","value":"true"}
{"_id":{"$oid":"5c655364635b7a0cb297b775"},"node":"public","typeName":"Boolean","property":"debugMode","value":"false"}
{"_id":{"$oid":"5c655364635b7a0cb297b77d"},"node":"public","typeName":"Int","property":"groundIterations","value":"1000000"}
{"_id":{"$oid":"5c655364635b7a0cb297b785"},"node":"public","typeName":"Int","property":"cores","value":"2"}
{"_id":{"$oid":"5c655364635b7a0cb297b791"},"node":"public","typeName":"Long","property":"memory","value":"3817865216"}
{"_id":{"$oid":"5c655364635b7a0cb297b799"},"node":"public","typeName":"Int","property":"latencyRecordingInterval","value":"1000"}
{"_id":{"$oid":"5c655364635b7a0cb297b7a9"},"node":"public","typeName":"Int","property":"performanceRecordingIntervalMs","value":"100"}
{"_id":{"$oid":"5c655364635b7a0cb297b7af"},"node":"public","typeName":"Int","property":"throughputRecordingIntervalMs","value":"100"}
{"_id":{"$oid":"5c655364635b7a0cb297b7b7"},"node":"public","typeName":"Long","property":"waitForBeingColdTimeoutMs","value":"30000"}
{"_id":{"$oid":"5c655364635b7a0cb297b7c5"},"node":"public","typeName":"Long","property":"waitForBeingColdIntervalMs","value":"5000"}
{"_id":{"$oid":"5c655364635b7a0cb297b7cf"},"node":"public","typeName":"Boolean","property":"skipExecution","value":"false"}
{"_id":{"$oid":"5c655364635b7a0cb297b7d9"},"node":"public","typeName":"Boolean","property":"invokeBeforeAllAndAfterAllEvenIfNoTestsAreExpected","value":"false"}
{"_id":{"$oid":"5c655364635b7a0cb297bac3"},"node":"purchasing","typeName":"Int","property":"baseIterations","value":"1000000"}
{"_id":{"$oid":"5c655364635b7a0cb297bad1"},"node":"purchasing","typeName":"Float","property":"baseIterationsCoefficient","value":"1.0"}
{"_id":{"$oid":"5c655364635b7a0cb297badb"},"node":"purchasing","typeName":"Int","property":"priorityClient","value":"1"}
{"_id":{"$oid":"5c655364635b7a0cb297bae9"},"node":"purchasing","typeName":"Int","property":"priorityEmployees","value":"1"}
{"_id":{"$oid":"5c655364635b7a0cb297baf1"},"node":"purchasing","typeName":"Int","property":"priorityPurchasing","value":"1"}
{"_id":{"$oid":"5c655364635b7a0cb297bafb"},"node":"purchasing","typeName":"Int","property":"priorityProduction","value":"1"}
{"_id":{"$oid":"5c655364635b7a0cb297bb05"},"node":"purchasing","typeName":"Int","property":"priorityPublic","value":"1"}
{"_id":{"$oid":"5c655364635b7a0cb297bb0f"},"node":"purchasing","typeName":"Boolean","property":"mongoTransferRecords","value":"true"}
{"_id":{"$oid":"5c655364635b7a0cb297bb17"},"node":"purchasing","typeName":"Boolean","property":"doWarmup","value":"true"}
{"_id":{"$oid":"5c655364635b7a0cb297bb21"},"node":"purchasing","typeName":"Boolean","property":"dbBackpressure","value":"true"}
{"_id":{"$oid":"5c655364635b7a0cb297bb2b"},"node":"purchasing","typeName":"Boolean","property":"debugMode","value":"false"}
{"_id":{"$oid":"5c655364635b7a0cb297bb3f"},"node":"purchasing","typeName":"Int","property":"groundIterations","value":"1000000"}
{"_id":{"$oid":"5c655364635b7a0cb297bb4b"},"node":"purchasing","typeName":"Int","property":"cores","value":"2"}
{"_id":{"$oid":"5c655364635b7a0cb297bb55"},"node":"purchasing","typeName":"Long","property":"memory","value":"3817865216"}
{"_id":{"$oid":"5c655364635b7a0cb297bb5d"},"node":"purchasing","typeName":"Int","property":"latencyRecordingInterval","value":"1000"}
{"_id":{"$oid":"5c655364635b7a0cb297bb69"},"node":"purchasing","typeName":"Int","property":"performanceRecordingIntervalMs","value":"100"}
{"_id":{"$oid":"5c655364635b7a0cb297bb73"},"node":"purchasing","typeName":"Int","property":"throughputRecordingIntervalMs","value":"100"}
{"_id":{"$oid":"5c655364635b7a0cb297bb7d"},"node":"purchasing","typeName":"Long","property":"waitForBeingColdTimeoutMs","value":"30000"}
{"_id":{"$oid":"5c655364635b7a0cb297bb87"},"node":"purchasing","typeName":"Long","property":"waitForBeingColdIntervalMs","value":"5000"}
{"_id":{"$oid":"5c655364635b7a0cb297bb91"},"node":"purchasing","typeName":"Boolean","property":"skipExecution","value":"false"}
{"_id":{"$oid":"5c655364635b7a0cb297bb9b"},"node":"purchasing","typeName":"Boolean","property":"invokeBeforeAllAndAfterAllEvenIfNoTestsAreExpected","value":"false"}
