{"_id":{"$oid":"5c668bcb635b7a0cb2236148"},"node":"production","typeName":"Int","property":"productCount","value":"5000"}
{"_id":{"$oid":"5c668bcb635b7a0cb223614a"},"node":"production","typeName":"Int","property":"factoryCount","value":"25000"}
{"_id":{"$oid":"5c668bcb635b7a0cb223614c"},"node":"production","typeName":"Float","property":"baseIterationsCoefficient","value":"0.05"}
{"_id":{"$oid":"5c668bcb635b7a0cb223614e"},"node":"production","typeName":"Int","property":"baseIterations","value":"50000"}
{"_id":{"$oid":"5c668bcb635b7a0cb2236150"},"node":"production","typeName":"Int","property":"priorityClient","value":"1"}
{"_id":{"$oid":"5c668bcb635b7a0cb2236152"},"node":"production","typeName":"Int","property":"priorityEmployees","value":"1"}
{"_id":{"$oid":"5c668bcb635b7a0cb2236154"},"node":"production","typeName":"Int","property":"priorityPurchasing","value":"1"}
{"_id":{"$oid":"5c668bcb635b7a0cb2236156"},"node":"production","typeName":"Int","property":"priorityProduction","value":"1"}
{"_id":{"$oid":"5c668bcb635b7a0cb2236158"},"node":"production","typeName":"Int","property":"priorityPublic","value":"1"}
{"_id":{"$oid":"5c668bcb635b7a0cb223615a"},"node":"production","typeName":"Boolean","property":"mongoTransferRecords","value":"true"}
{"_id":{"$oid":"5c668bcb635b7a0cb223615c"},"node":"production","typeName":"Boolean","property":"doWarmup","value":"true"}
{"_id":{"$oid":"5c668bcb635b7a0cb223615e"},"node":"production","typeName":"Boolean","property":"dbBackpressure","value":"true"}
{"_id":{"$oid":"5c668bcb635b7a0cb2236160"},"node":"production","typeName":"Boolean","property":"debugMode","value":"false"}
{"_id":{"$oid":"5c668bcb635b7a0cb2236162"},"node":"production","typeName":"Int","property":"groundIterations","value":"1000000"}
{"_id":{"$oid":"5c668bcb635b7a0cb2236164"},"node":"production","typeName":"Int","property":"cores","value":"2"}
{"_id":{"$oid":"5c668bcb635b7a0cb2236166"},"node":"production","typeName":"Long","property":"memory","value":"3685744640"}
{"_id":{"$oid":"5c668bcb635b7a0cb2236168"},"node":"production","typeName":"Int","property":"latencyRecordingInterval","value":"1000"}
{"_id":{"$oid":"5c668bcb635b7a0cb223616a"},"node":"production","typeName":"Int","property":"performanceRecordingIntervalMs","value":"100"}
{"_id":{"$oid":"5c668bcb635b7a0cb223616c"},"node":"production","typeName":"Int","property":"throughputRecordingIntervalMs","value":"100"}
{"_id":{"$oid":"5c668bcb635b7a0cb223616e"},"node":"production","typeName":"Long","property":"waitForBeingColdTimeoutMs","value":"30000"}
{"_id":{"$oid":"5c668bcb635b7a0cb2236170"},"node":"production","typeName":"Long","property":"waitForBeingColdIntervalMs","value":"5000"}
{"_id":{"$oid":"5c668bcb635b7a0cb2236172"},"node":"production","typeName":"Boolean","property":"skipExecution","value":"false"}
{"_id":{"$oid":"5c668bcb635b7a0cb2236174"},"node":"production","typeName":"Boolean","property":"invokeBeforeAllAndAfterAllEvenIfNoTestsAreExpected","value":"false"}
{"_id":{"$oid":"5c668bcc635b7a0cb22361bc"},"node":"client","typeName":"JSON","property":"placement","value":"{\"cost\":1.491974502122921,\"solutions\":[{\"placements\":[{\"operator\":0,\"host\":0},{\"operator\":1,\"host\":0},{\"operator\":2,\"host\":0},{\"operator\":3,\"host\":0},{\"operator\":4,\"host\":0},{\"operator\":5,\"host\":0},{\"operator\":6,\"host\":2},{\"operator\":7,\"host\":2},{\"operator\":8,\"host\":2}]}],\"selectedSolution\":0,\"operators\":[{\"id\":0,\"operatorName\":\"actor\",\"hostCandidates\":[0,1,2,3,4],\"selectivity\":1.0,\"load\":0.0,\"outgoingLink\":1000.0},{\"id\":1,\"operatorName\":\"re-classification\",\"hostCandidates\":[0,1,2,3,4],\"selectivity\":1.0,\"load\":0.0,\"outgoingLink\":1000.0},{\"id\":2,\"operatorName\":\"selection\",\"hostCandidates\":[0,1,2,3,4],\"selectivity\":0.5,\"load\":1000.0,\"outgoingLink\":500.0},{\"id\":3,\"operatorName\":\"actor\",\"hostCandidates\":[0,1,2,3,4],\"selectivity\":1.0,\"load\":0.0,\"outgoingLink\":1000.0},{\"id\":4,\"operatorName\":\"re-classification\",\"hostCandidates\":[0,1,2,3,4],\"selectivity\":1.0,\"load\":0.0,\"outgoingLink\":1000.0},{\"id\":5,\"operatorName\":\"selection\",\"hostCandidates\":[0,1,2,3,4],\"selectivity\":0.10000000149011612,\"load\":1000.0,\"outgoingLink\":100.00000149011612},{\"id\":6,\"operatorName\":\"cross-product\",\"hostCandidates\":[0,1,2,3,4],\"selectivity\":1000.0,\"load\":50000.00074505806,\"outgoingLink\":600000.0014901161},{\"id\":7,\"operatorName\":\"projection\",\"hostCandidates\":[0,1,2,3,4],\"selectivity\":1.0,\"load\":600000.0014901161,\"outgoingLink\":600000.0014901161},{\"id\":8,\"operatorName\":\"root\",\"hostCandidates\":[0,1,2,3,4],\"selectivity\":1.0,\"load\":0.0,\"outgoingLink\":600000.0014901161}],\"links\":[{\"sender\":0,\"receiver\":1,\"load\":1000.0},{\"sender\":1,\"receiver\":2,\"load\":1000.0},{\"sender\":3,\"receiver\":4,\"load\":1000.0},{\"sender\":4,\"receiver\":5,\"load\":1000.0},{\"sender\":2,\"receiver\":6,\"load\":500.0},{\"sender\":5,\"receiver\":6,\"load\":100.00000149011612},{\"sender\":6,\"receiver\":7,\"load\":600000.0014901161},{\"sender\":7,\"receiver\":8,\"load\":600000.0014901161}],\"hosts\":[{\"id\":0,\"name\":\"public-host\"},{\"id\":1,\"name\":\"employees-host\"},{\"id\":2,\"name\":\"clients-host\"},{\"id\":3,\"name\":\"production-host\"},{\"id\":4,\"name\":\"purchasing-host\"}],\"duration\":206,\"timedOut\":false}"}
{"_id":{"$oid":"5c668bcc635b7a0cb22361be"},"node":"client","typeName":"Int","property":"productCount","value":"5000"}
{"_id":{"$oid":"5c668bcc635b7a0cb22361c0"},"node":"client","typeName":"Int","property":"factoryCount","value":"25000"}
{"_id":{"$oid":"5c668bcc635b7a0cb22361c2"},"node":"client","typeName":"Float","property":"baseIterationsCoefficient","value":"0.05"}
{"_id":{"$oid":"5c668bcc635b7a0cb22361c4"},"node":"client","typeName":"Int","property":"baseIterations","value":"50000"}
{"_id":{"$oid":"5c668bcc635b7a0cb22361c6"},"node":"client","typeName":"Int","property":"priorityClient","value":"1"}
{"_id":{"$oid":"5c668bcc635b7a0cb22361c8"},"node":"client","typeName":"Int","property":"priorityEmployees","value":"1"}
{"_id":{"$oid":"5c668bcc635b7a0cb22361ca"},"node":"client","typeName":"Int","property":"priorityPurchasing","value":"1"}
{"_id":{"$oid":"5c668bcc635b7a0cb22361cc"},"node":"client","typeName":"Int","property":"priorityProduction","value":"1"}
{"_id":{"$oid":"5c668bcc635b7a0cb22361ce"},"node":"client","typeName":"Int","property":"priorityPublic","value":"1"}
{"_id":{"$oid":"5c668bcc635b7a0cb22361d0"},"node":"client","typeName":"Boolean","property":"mongoTransferRecords","value":"true"}
{"_id":{"$oid":"5c668bcc635b7a0cb22361d2"},"node":"client","typeName":"Boolean","property":"doWarmup","value":"true"}
{"_id":{"$oid":"5c668bcc635b7a0cb22361d4"},"node":"client","typeName":"Boolean","property":"dbBackpressure","value":"true"}
{"_id":{"$oid":"5c668bcc635b7a0cb22361d6"},"node":"client","typeName":"Boolean","property":"debugMode","value":"false"}
{"_id":{"$oid":"5c668bcc635b7a0cb22361d8"},"node":"client","typeName":"Int","property":"groundIterations","value":"1000000"}
{"_id":{"$oid":"5c668bcc635b7a0cb22361da"},"node":"client","typeName":"Int","property":"cores","value":"2"}
{"_id":{"$oid":"5c668bcc635b7a0cb22361dc"},"node":"client","typeName":"Long","property":"memory","value":"3817865216"}
{"_id":{"$oid":"5c668bcc635b7a0cb22361de"},"node":"client","typeName":"Int","property":"latencyRecordingInterval","value":"1000"}
{"_id":{"$oid":"5c668bcc635b7a0cb22361e0"},"node":"client","typeName":"Int","property":"performanceRecordingIntervalMs","value":"100"}
{"_id":{"$oid":"5c668bcc635b7a0cb22361e2"},"node":"client","typeName":"Int","property":"throughputRecordingIntervalMs","value":"100"}
{"_id":{"$oid":"5c668bcc635b7a0cb22361e4"},"node":"client","typeName":"Long","property":"waitForBeingColdTimeoutMs","value":"30000"}
{"_id":{"$oid":"5c668bcc635b7a0cb22361e6"},"node":"client","typeName":"Long","property":"waitForBeingColdIntervalMs","value":"5000"}
{"_id":{"$oid":"5c668bcc635b7a0cb22361e8"},"node":"client","typeName":"Boolean","property":"skipExecution","value":"false"}
{"_id":{"$oid":"5c668bcc635b7a0cb22361ea"},"node":"client","typeName":"Boolean","property":"invokeBeforeAllAndAfterAllEvenIfNoTestsAreExpected","value":"false"}
{"_id":{"$oid":"5c668bcc635b7a0cb2236380"},"node":"public","typeName":"Int","property":"productCount","value":"5000"}
{"_id":{"$oid":"5c668bcc635b7a0cb2236384"},"node":"public","typeName":"Int","property":"factoryCount","value":"25000"}
{"_id":{"$oid":"5c668bcc635b7a0cb2236390"},"node":"public","typeName":"Float","property":"baseIterationsCoefficient","value":"0.05"}
{"_id":{"$oid":"5c668bcc635b7a0cb2236394"},"node":"public","typeName":"Int","property":"baseIterations","value":"50000"}
{"_id":{"$oid":"5c668bcc635b7a0cb2236398"},"node":"public","typeName":"Int","property":"priorityClient","value":"1"}
{"_id":{"$oid":"5c668bcc635b7a0cb223639e"},"node":"public","typeName":"Int","property":"priorityEmployees","value":"1"}
{"_id":{"$oid":"5c668bcc635b7a0cb22363a2"},"node":"public","typeName":"Int","property":"priorityPurchasing","value":"1"}
{"_id":{"$oid":"5c668bcc635b7a0cb22363a6"},"node":"public","typeName":"Int","property":"priorityProduction","value":"1"}
{"_id":{"$oid":"5c668bcc635b7a0cb22363aa"},"node":"public","typeName":"Int","property":"priorityPublic","value":"1"}
{"_id":{"$oid":"5c668bcc635b7a0cb22363ae"},"node":"public","typeName":"Boolean","property":"mongoTransferRecords","value":"true"}
{"_id":{"$oid":"5c668bcc635b7a0cb22363b2"},"node":"public","typeName":"Boolean","property":"doWarmup","value":"true"}
{"_id":{"$oid":"5c668bcc635b7a0cb22363b8"},"node":"public","typeName":"Boolean","property":"dbBackpressure","value":"true"}
{"_id":{"$oid":"5c668bcc635b7a0cb22363bc"},"node":"public","typeName":"Boolean","property":"debugMode","value":"false"}
{"_id":{"$oid":"5c668bcc635b7a0cb22363c0"},"node":"public","typeName":"Int","property":"groundIterations","value":"1000000"}
{"_id":{"$oid":"5c668bcc635b7a0cb22363c4"},"node":"public","typeName":"Int","property":"cores","value":"2"}
{"_id":{"$oid":"5c668bcc635b7a0cb22363d0"},"node":"public","typeName":"Long","property":"memory","value":"3817865216"}
{"_id":{"$oid":"5c668bcc635b7a0cb22363d4"},"node":"public","typeName":"Int","property":"latencyRecordingInterval","value":"1000"}
{"_id":{"$oid":"5c668bcc635b7a0cb22363d8"},"node":"public","typeName":"Int","property":"performanceRecordingIntervalMs","value":"100"}
{"_id":{"$oid":"5c668bcc635b7a0cb22363dc"},"node":"public","typeName":"Int","property":"throughputRecordingIntervalMs","value":"100"}
{"_id":{"$oid":"5c668bcc635b7a0cb22363ea"},"node":"public","typeName":"Long","property":"waitForBeingColdTimeoutMs","value":"30000"}
{"_id":{"$oid":"5c668bcc635b7a0cb22363f4"},"node":"public","typeName":"Long","property":"waitForBeingColdIntervalMs","value":"5000"}
{"_id":{"$oid":"5c668bcc635b7a0cb22363f8"},"node":"public","typeName":"Boolean","property":"skipExecution","value":"false"}
{"_id":{"$oid":"5c668bcc635b7a0cb2236402"},"node":"public","typeName":"Boolean","property":"invokeBeforeAllAndAfterAllEvenIfNoTestsAreExpected","value":"false"}
{"_id":{"$oid":"5c668bcc635b7a0cb2236a5e"},"node":"purchasing","typeName":"Int","property":"productCount","value":"5000"}
{"_id":{"$oid":"5c668bcc635b7a0cb2236a64"},"node":"purchasing","typeName":"Int","property":"factoryCount","value":"25000"}
{"_id":{"$oid":"5c668bcc635b7a0cb2236a68"},"node":"purchasing","typeName":"Float","property":"baseIterationsCoefficient","value":"0.05"}
{"_id":{"$oid":"5c668bcc635b7a0cb2236a6e"},"node":"purchasing","typeName":"Int","property":"baseIterations","value":"50000"}
{"_id":{"$oid":"5c668bcc635b7a0cb2236a72"},"node":"purchasing","typeName":"Int","property":"priorityClient","value":"1"}
{"_id":{"$oid":"5c668bcc635b7a0cb2236a76"},"node":"purchasing","typeName":"Int","property":"priorityEmployees","value":"1"}
{"_id":{"$oid":"5c668bcc635b7a0cb2236a7a"},"node":"purchasing","typeName":"Int","property":"priorityPurchasing","value":"1"}
{"_id":{"$oid":"5c668bcc635b7a0cb2236a7e"},"node":"purchasing","typeName":"Int","property":"priorityProduction","value":"1"}
{"_id":{"$oid":"5c668bcc635b7a0cb2236a82"},"node":"purchasing","typeName":"Int","property":"priorityPublic","value":"1"}
{"_id":{"$oid":"5c668bcc635b7a0cb2236a88"},"node":"purchasing","typeName":"Boolean","property":"mongoTransferRecords","value":"true"}
{"_id":{"$oid":"5c668bcc635b7a0cb2236a8c"},"node":"purchasing","typeName":"Boolean","property":"doWarmup","value":"true"}
{"_id":{"$oid":"5c668bcc635b7a0cb2236a90"},"node":"purchasing","typeName":"Boolean","property":"dbBackpressure","value":"true"}
{"_id":{"$oid":"5c668bcc635b7a0cb2236a94"},"node":"purchasing","typeName":"Boolean","property":"debugMode","value":"false"}
{"_id":{"$oid":"5c668bcc635b7a0cb2236a98"},"node":"purchasing","typeName":"Int","property":"groundIterations","value":"1000000"}
{"_id":{"$oid":"5c668bcc635b7a0cb2236a9c"},"node":"purchasing","typeName":"Int","property":"cores","value":"2"}
{"_id":{"$oid":"5c668bcc635b7a0cb2236aa0"},"node":"purchasing","typeName":"Long","property":"memory","value":"3817865216"}
{"_id":{"$oid":"5c668bcc635b7a0cb2236aaa"},"node":"purchasing","typeName":"Int","property":"latencyRecordingInterval","value":"1000"}
{"_id":{"$oid":"5c668bcc635b7a0cb2236aae"},"node":"purchasing","typeName":"Int","property":"performanceRecordingIntervalMs","value":"100"}
{"_id":{"$oid":"5c668bcc635b7a0cb2236ab2"},"node":"purchasing","typeName":"Int","property":"throughputRecordingIntervalMs","value":"100"}
{"_id":{"$oid":"5c668bcc635b7a0cb2236ab6"},"node":"purchasing","typeName":"Long","property":"waitForBeingColdTimeoutMs","value":"30000"}
{"_id":{"$oid":"5c668bcc635b7a0cb2236aba"},"node":"purchasing","typeName":"Long","property":"waitForBeingColdIntervalMs","value":"5000"}
{"_id":{"$oid":"5c668bcc635b7a0cb2236ac0"},"node":"purchasing","typeName":"Boolean","property":"skipExecution","value":"false"}
{"_id":{"$oid":"5c668bcc635b7a0cb2236ac4"},"node":"purchasing","typeName":"Boolean","property":"invokeBeforeAllAndAfterAllEvenIfNoTestsAreExpected","value":"false"}
{"_id":{"$oid":"5c668bcd635b7a0cb2236c20"},"node":"employees","typeName":"Int","property":"productCount","value":"5000"}
{"_id":{"$oid":"5c668bcd635b7a0cb2236c26"},"node":"employees","typeName":"Int","property":"factoryCount","value":"25000"}
{"_id":{"$oid":"5c668bcd635b7a0cb2236c2a"},"node":"employees","typeName":"Float","property":"baseIterationsCoefficient","value":"0.05"}
{"_id":{"$oid":"5c668bcd635b7a0cb2236c2e"},"node":"employees","typeName":"Int","property":"baseIterations","value":"50000"}
{"_id":{"$oid":"5c668bcd635b7a0cb2236c34"},"node":"employees","typeName":"Int","property":"priorityClient","value":"1"}
{"_id":{"$oid":"5c668bcd635b7a0cb2236c38"},"node":"employees","typeName":"Int","property":"priorityEmployees","value":"1"}
{"_id":{"$oid":"5c668bcd635b7a0cb2236c3c"},"node":"employees","typeName":"Int","property":"priorityPurchasing","value":"1"}
{"_id":{"$oid":"5c668bcd635b7a0cb2236c40"},"node":"employees","typeName":"Int","property":"priorityProduction","value":"1"}
{"_id":{"$oid":"5c668bcd635b7a0cb2236c44"},"node":"employees","typeName":"Int","property":"priorityPublic","value":"1"}
{"_id":{"$oid":"5c668bcd635b7a0cb2236c48"},"node":"employees","typeName":"Boolean","property":"mongoTransferRecords","value":"true"}
{"_id":{"$oid":"5c668bcd635b7a0cb2236c4c"},"node":"employees","typeName":"Boolean","property":"doWarmup","value":"true"}
{"_id":{"$oid":"5c668bcd635b7a0cb2236c50"},"node":"employees","typeName":"Boolean","property":"dbBackpressure","value":"true"}
{"_id":{"$oid":"5c668bcd635b7a0cb2236c56"},"node":"employees","typeName":"Boolean","property":"debugMode","value":"false"}
{"_id":{"$oid":"5c668bcd635b7a0cb2236c5a"},"node":"employees","typeName":"Int","property":"groundIterations","value":"1000000"}
{"_id":{"$oid":"5c668bcd635b7a0cb2236c5e"},"node":"employees","typeName":"Int","property":"cores","value":"2"}
{"_id":{"$oid":"5c668bcd635b7a0cb2236c62"},"node":"employees","typeName":"Long","property":"memory","value":"3817865216"}
{"_id":{"$oid":"5c668bcd635b7a0cb2236c66"},"node":"employees","typeName":"Int","property":"latencyRecordingInterval","value":"1000"}
{"_id":{"$oid":"5c668bcd635b7a0cb2236c6a"},"node":"employees","typeName":"Int","property":"performanceRecordingIntervalMs","value":"100"}
{"_id":{"$oid":"5c668bcd635b7a0cb2236c6e"},"node":"employees","typeName":"Int","property":"throughputRecordingIntervalMs","value":"100"}
{"_id":{"$oid":"5c668bcd635b7a0cb2236c74"},"node":"employees","typeName":"Long","property":"waitForBeingColdTimeoutMs","value":"30000"}
{"_id":{"$oid":"5c668bcd635b7a0cb2236c78"},"node":"employees","typeName":"Long","property":"waitForBeingColdIntervalMs","value":"5000"}
{"_id":{"$oid":"5c668bcd635b7a0cb2236c7c"},"node":"employees","typeName":"Boolean","property":"skipExecution","value":"false"}
{"_id":{"$oid":"5c668bcd635b7a0cb2236c80"},"node":"employees","typeName":"Boolean","property":"invokeBeforeAllAndAfterAllEvenIfNoTestsAreExpected","value":"false"}
