{"_id":{"$oid":"5c72594ef7797b8298f0779e"},"node":"production","typeName":"Int","property":"baseIterations","value":"1000000"}
{"_id":{"$oid":"5c72594ef7797b8298f077a0"},"node":"production","typeName":"Float","property":"baseIterationsCoefficient","value":"1.0"}
{"_id":{"$oid":"5c72594ef7797b8298f077a2"},"node":"production","typeName":"Int","property":"priorityClient","value":"1"}
{"_id":{"$oid":"5c72594ef7797b8298f077a4"},"node":"production","typeName":"Int","property":"priorityEmployees","value":"2"}
{"_id":{"$oid":"5c72594ef7797b8298f077a6"},"node":"production","typeName":"Int","property":"priorityPurchasing","value":"4"}
{"_id":{"$oid":"5c72594ef7797b8298f077a8"},"node":"production","typeName":"Int","property":"priorityProduction","value":"8"}
{"_id":{"$oid":"5c72594ef7797b8298f077aa"},"node":"production","typeName":"Int","property":"priorityPublic","value":"2"}
{"_id":{"$oid":"5c72594ef7797b8298f077ac"},"node":"production","typeName":"Boolean","property":"mongoTransferRecords","value":"true"}
{"_id":{"$oid":"5c72594ef7797b8298f077ae"},"node":"production","typeName":"Boolean","property":"doWarmup","value":"true"}
{"_id":{"$oid":"5c72594ef7797b8298f077b0"},"node":"production","typeName":"Boolean","property":"dbBackpressure","value":"true"}
{"_id":{"$oid":"5c72594ef7797b8298f077b2"},"node":"production","typeName":"Boolean","property":"debugMode","value":"false"}
{"_id":{"$oid":"5c72594ef7797b8298f077b4"},"node":"production","typeName":"Int","property":"groundIterations","value":"1000000"}
{"_id":{"$oid":"5c72594ef7797b8298f077b6"},"node":"production","typeName":"Int","property":"cores","value":"4"}
{"_id":{"$oid":"5c72594ef7797b8298f077b8"},"node":"production","typeName":"Long","property":"memory","value":"7635730432"}
{"_id":{"$oid":"5c72594ef7797b8298f077ba"},"node":"production","typeName":"Int","property":"latencyRecordingInterval","value":"1000"}
{"_id":{"$oid":"5c72594ef7797b8298f077bc"},"node":"production","typeName":"Int","property":"performanceRecordingIntervalMs","value":"100"}
{"_id":{"$oid":"5c72594ef7797b8298f077be"},"node":"production","typeName":"Int","property":"throughputRecordingIntervalMs","value":"100"}
{"_id":{"$oid":"5c72594ef7797b8298f077c0"},"node":"production","typeName":"Long","property":"waitForBeingColdTimeoutMs","value":"30000"}
{"_id":{"$oid":"5c72594ef7797b8298f077c2"},"node":"production","typeName":"Long","property":"waitForBeingColdIntervalMs","value":"5000"}
{"_id":{"$oid":"5c72594ef7797b8298f077c4"},"node":"production","typeName":"Boolean","property":"skipExecution","value":"false"}
{"_id":{"$oid":"5c72594ef7797b8298f077c6"},"node":"production","typeName":"Boolean","property":"invokeBeforeAllAndAfterAllEvenIfNoTestsAreExpected","value":"false"}
{"_id":{"$oid":"5c72594ef7797b8298f0799e"},"node":"purchasing","typeName":"Int","property":"baseIterations","value":"1000000"}
{"_id":{"$oid":"5c72594ef7797b8298f079a0"},"node":"purchasing","typeName":"Float","property":"baseIterationsCoefficient","value":"1.0"}
{"_id":{"$oid":"5c72594ef7797b8298f079a2"},"node":"purchasing","typeName":"Int","property":"priorityClient","value":"1"}
{"_id":{"$oid":"5c72594ef7797b8298f079a4"},"node":"purchasing","typeName":"Int","property":"priorityEmployees","value":"2"}
{"_id":{"$oid":"5c72594ef7797b8298f079a6"},"node":"purchasing","typeName":"Int","property":"priorityPurchasing","value":"4"}
{"_id":{"$oid":"5c72594ef7797b8298f079a8"},"node":"purchasing","typeName":"Int","property":"priorityProduction","value":"8"}
{"_id":{"$oid":"5c72594ef7797b8298f079aa"},"node":"purchasing","typeName":"Int","property":"priorityPublic","value":"2"}
{"_id":{"$oid":"5c72594ef7797b8298f079ac"},"node":"purchasing","typeName":"Boolean","property":"mongoTransferRecords","value":"true"}
{"_id":{"$oid":"5c72594ef7797b8298f079ae"},"node":"purchasing","typeName":"Boolean","property":"doWarmup","value":"true"}
{"_id":{"$oid":"5c72594ef7797b8298f079b0"},"node":"purchasing","typeName":"Boolean","property":"dbBackpressure","value":"true"}
{"_id":{"$oid":"5c72594ef7797b8298f079b2"},"node":"purchasing","typeName":"Boolean","property":"debugMode","value":"false"}
{"_id":{"$oid":"5c72594ef7797b8298f079b4"},"node":"purchasing","typeName":"Int","property":"groundIterations","value":"1000000"}
{"_id":{"$oid":"5c72594ef7797b8298f079b6"},"node":"purchasing","typeName":"Int","property":"cores","value":"2"}
{"_id":{"$oid":"5c72594ef7797b8298f079b8"},"node":"purchasing","typeName":"Long","property":"memory","value":"3817865216"}
{"_id":{"$oid":"5c72594ef7797b8298f079ba"},"node":"purchasing","typeName":"Int","property":"latencyRecordingInterval","value":"1000"}
{"_id":{"$oid":"5c72594ef7797b8298f079bc"},"node":"purchasing","typeName":"Int","property":"performanceRecordingIntervalMs","value":"100"}
{"_id":{"$oid":"5c72594ef7797b8298f079be"},"node":"purchasing","typeName":"Int","property":"throughputRecordingIntervalMs","value":"100"}
{"_id":{"$oid":"5c72594ef7797b8298f079c0"},"node":"purchasing","typeName":"Long","property":"waitForBeingColdTimeoutMs","value":"30000"}
{"_id":{"$oid":"5c72594ef7797b8298f079c2"},"node":"purchasing","typeName":"Long","property":"waitForBeingColdIntervalMs","value":"5000"}
{"_id":{"$oid":"5c72594ef7797b8298f079c4"},"node":"purchasing","typeName":"Boolean","property":"skipExecution","value":"false"}
{"_id":{"$oid":"5c72594ef7797b8298f079c6"},"node":"purchasing","typeName":"Boolean","property":"invokeBeforeAllAndAfterAllEvenIfNoTestsAreExpected","value":"false"}
{"_id":{"$oid":"5c725951f7797b8298f07d2e"},"node":"client","typeName":"JSON","property":"placement","value":"{\"cost\":0.005726311885725051,\"solutions\":[{\"placements\":[{\"operator\":0,\"host\":0},{\"operator\":1,\"host\":0},{\"operator\":2,\"host\":0},{\"operator\":3,\"host\":3},{\"operator\":4,\"host\":3},{\"operator\":5,\"host\":3},{\"operator\":6,\"host\":3},{\"operator\":7,\"host\":3},{\"operator\":8,\"host\":3},{\"operator\":9,\"host\":3},{\"operator\":10,\"host\":0},{\"operator\":11,\"host\":0},{\"operator\":12,\"host\":4}]}],\"selectedSolution\":0,\"operators\":[{\"id\":0,\"operatorName\":\"actor\",\"hostCandidates\":[0,1,2,3,4],\"selectivity\":1.0,\"load\":0.0,\"outgoingLink\":1000.0},{\"id\":1,\"operatorName\":\"re-classification\",\"hostCandidates\":[0,1,2,3,4],\"selectivity\":1.0,\"load\":0.0,\"outgoingLink\":1000.0},{\"id\":2,\"operatorName\":\"selection\",\"hostCandidates\":[0,1,2,3,4],\"selectivity\":1.0,\"load\":1.0,\"outgoingLink\":1000.0},{\"id\":3,\"operatorName\":\"actor\",\"hostCandidates\":[0,1,2,3,4],\"selectivity\":1.0,\"load\":0.0,\"outgoingLink\":1000.0},{\"id\":4,\"operatorName\":\"re-classification\",\"hostCandidates\":[0,1,2,3,4],\"selectivity\":1.0,\"load\":0.0,\"outgoingLink\":1000.0},{\"id\":5,\"operatorName\":\"selection\",\"hostCandidates\":[0,1,2,3,4],\"selectivity\":0.20000000298023224,\"load\":1.0,\"outgoingLink\":200.00000298023224},{\"id\":6,\"operatorName\":\"actor\",\"hostCandidates\":[0,1,2,3,4],\"selectivity\":1.0,\"load\":0.0,\"outgoingLink\":1000.0},{\"id\":7,\"operatorName\":\"re-classification\",\"hostCandidates\":[0,1,2,3,4],\"selectivity\":1.0,\"load\":0.0,\"outgoingLink\":1000.0},{\"id\":8,\"operatorName\":\"selection\",\"hostCandidates\":[0,1,2,3,4],\"selectivity\":0.20000000298023224,\"load\":1.0,\"outgoingLink\":200.00000298023224},{\"id\":9,\"operatorName\":\"equi-join\",\"hostCandidates\":[0,1,2,3,4],\"selectivity\":0.3333333432674408,\"load\":4.0,\"outgoingLink\":133.33333929379788},{\"id\":10,\"operatorName\":\"equi-join\",\"hostCandidates\":[0,1,2,3,4],\"selectivity\":0.09090909361839294,\"load\":4.0,\"outgoingLink\":103.03030664270577},{\"id\":11,\"operatorName\":\"projection\",\"hostCandidates\":[0,1,2,3,4],\"selectivity\":1.0,\"load\":1.0,\"outgoingLink\":103.03030664270577},{\"id\":12,\"operatorName\":\"root\",\"hostCandidates\":[0,1,2,3,4],\"selectivity\":1.0,\"load\":0.0,\"outgoingLink\":103.03030664270577}],\"links\":[{\"sender\":0,\"receiver\":1,\"load\":1000.0},{\"sender\":1,\"receiver\":2,\"load\":1000.0},{\"sender\":3,\"receiver\":4,\"load\":1000.0},{\"sender\":4,\"receiver\":5,\"load\":1000.0},{\"sender\":6,\"receiver\":7,\"load\":1000.0},{\"sender\":7,\"receiver\":8,\"load\":1000.0},{\"sender\":5,\"receiver\":9,\"load\":200.00000298023224},{\"sender\":8,\"receiver\":9,\"load\":200.00000298023224},{\"sender\":2,\"receiver\":10,\"load\":1000.0},{\"sender\":9,\"receiver\":10,\"load\":133.33333929379788},{\"sender\":10,\"receiver\":11,\"load\":103.03030664270577},{\"sender\":11,\"receiver\":12,\"load\":103.03030664270577}],\"hosts\":[{\"id\":0,\"name\":\"production-host\"},{\"id\":1,\"name\":\"public-host\"},{\"id\":2,\"name\":\"employees-host\"},{\"id\":3,\"name\":\"purchasing-host\"},{\"id\":4,\"name\":\"clients-host\"}],\"duration\":917,\"timedOut\":false}"}
{"_id":{"$oid":"5c725951f7797b8298f07d30"},"node":"client","typeName":"Int","property":"baseIterations","value":"1000000"}
{"_id":{"$oid":"5c725951f7797b8298f07d32"},"node":"client","typeName":"Float","property":"baseIterationsCoefficient","value":"1.0"}
{"_id":{"$oid":"5c725951f7797b8298f07d34"},"node":"client","typeName":"Int","property":"priorityClient","value":"1"}
{"_id":{"$oid":"5c725951f7797b8298f07d36"},"node":"client","typeName":"Int","property":"priorityEmployees","value":"2"}
{"_id":{"$oid":"5c725951f7797b8298f07d38"},"node":"client","typeName":"Int","property":"priorityPurchasing","value":"4"}
{"_id":{"$oid":"5c725951f7797b8298f07d3a"},"node":"client","typeName":"Int","property":"priorityProduction","value":"8"}
{"_id":{"$oid":"5c725951f7797b8298f07d3c"},"node":"client","typeName":"Int","property":"priorityPublic","value":"2"}
{"_id":{"$oid":"5c725951f7797b8298f07d3e"},"node":"client","typeName":"Boolean","property":"mongoTransferRecords","value":"true"}
{"_id":{"$oid":"5c725951f7797b8298f07d40"},"node":"client","typeName":"Boolean","property":"doWarmup","value":"true"}
{"_id":{"$oid":"5c725951f7797b8298f07d42"},"node":"client","typeName":"Boolean","property":"dbBackpressure","value":"true"}
{"_id":{"$oid":"5c725951f7797b8298f07d44"},"node":"client","typeName":"Boolean","property":"debugMode","value":"false"}
{"_id":{"$oid":"5c725951f7797b8298f07d46"},"node":"client","typeName":"Int","property":"groundIterations","value":"1000000"}
{"_id":{"$oid":"5c725951f7797b8298f07d48"},"node":"client","typeName":"Int","property":"cores","value":"2"}
{"_id":{"$oid":"5c725951f7797b8298f07d4a"},"node":"client","typeName":"Long","property":"memory","value":"3817865216"}
{"_id":{"$oid":"5c725951f7797b8298f07d4c"},"node":"client","typeName":"Int","property":"latencyRecordingInterval","value":"1000"}
{"_id":{"$oid":"5c725951f7797b8298f07d4e"},"node":"client","typeName":"Int","property":"performanceRecordingIntervalMs","value":"100"}
{"_id":{"$oid":"5c725951f7797b8298f07d50"},"node":"client","typeName":"Int","property":"throughputRecordingIntervalMs","value":"100"}
{"_id":{"$oid":"5c725951f7797b8298f07d52"},"node":"client","typeName":"Long","property":"waitForBeingColdTimeoutMs","value":"30000"}
{"_id":{"$oid":"5c725951f7797b8298f07d54"},"node":"client","typeName":"Long","property":"waitForBeingColdIntervalMs","value":"5000"}
{"_id":{"$oid":"5c725951f7797b8298f07d56"},"node":"client","typeName":"Boolean","property":"skipExecution","value":"false"}
{"_id":{"$oid":"5c725951f7797b8298f07d58"},"node":"client","typeName":"Boolean","property":"invokeBeforeAllAndAfterAllEvenIfNoTestsAreExpected","value":"false"}
{"_id":{"$oid":"5c725951f7797b8298f07db8"},"node":"employees","typeName":"Int","property":"baseIterations","value":"1000000"}
{"_id":{"$oid":"5c725951f7797b8298f07dbe"},"node":"employees","typeName":"Float","property":"baseIterationsCoefficient","value":"1.0"}
{"_id":{"$oid":"5c725951f7797b8298f07dc2"},"node":"employees","typeName":"Int","property":"priorityClient","value":"1"}
{"_id":{"$oid":"5c725951f7797b8298f07dc4"},"node":"employees","typeName":"Int","property":"priorityEmployees","value":"2"}
{"_id":{"$oid":"5c725951f7797b8298f07dc6"},"node":"employees","typeName":"Int","property":"priorityPurchasing","value":"4"}
{"_id":{"$oid":"5c725951f7797b8298f07dc8"},"node":"employees","typeName":"Int","property":"priorityProduction","value":"8"}
{"_id":{"$oid":"5c725951f7797b8298f07dca"},"node":"employees","typeName":"Int","property":"priorityPublic","value":"2"}
{"_id":{"$oid":"5c725951f7797b8298f07dcc"},"node":"employees","typeName":"Boolean","property":"mongoTransferRecords","value":"true"}
{"_id":{"$oid":"5c725951f7797b8298f07dce"},"node":"employees","typeName":"Boolean","property":"doWarmup","value":"true"}
{"_id":{"$oid":"5c725951f7797b8298f07dd0"},"node":"employees","typeName":"Boolean","property":"dbBackpressure","value":"true"}
{"_id":{"$oid":"5c725951f7797b8298f07dd2"},"node":"employees","typeName":"Boolean","property":"debugMode","value":"false"}
{"_id":{"$oid":"5c725951f7797b8298f07dd4"},"node":"employees","typeName":"Int","property":"groundIterations","value":"1000000"}
{"_id":{"$oid":"5c725951f7797b8298f07dd6"},"node":"employees","typeName":"Int","property":"cores","value":"2"}
{"_id":{"$oid":"5c725951f7797b8298f07dd8"},"node":"employees","typeName":"Long","property":"memory","value":"3817865216"}
{"_id":{"$oid":"5c725951f7797b8298f07dda"},"node":"employees","typeName":"Int","property":"latencyRecordingInterval","value":"1000"}
{"_id":{"$oid":"5c725951f7797b8298f07ddc"},"node":"employees","typeName":"Int","property":"performanceRecordingIntervalMs","value":"100"}
{"_id":{"$oid":"5c725951f7797b8298f07dde"},"node":"employees","typeName":"Int","property":"throughputRecordingIntervalMs","value":"100"}
{"_id":{"$oid":"5c725951f7797b8298f07de0"},"node":"employees","typeName":"Long","property":"waitForBeingColdTimeoutMs","value":"30000"}
{"_id":{"$oid":"5c725951f7797b8298f07de2"},"node":"employees","typeName":"Long","property":"waitForBeingColdIntervalMs","value":"5000"}
{"_id":{"$oid":"5c725951f7797b8298f07de4"},"node":"employees","typeName":"Boolean","property":"skipExecution","value":"false"}
{"_id":{"$oid":"5c725951f7797b8298f07de6"},"node":"employees","typeName":"Boolean","property":"invokeBeforeAllAndAfterAllEvenIfNoTestsAreExpected","value":"false"}
{"_id":{"$oid":"5c725951f7797b8298f07e64"},"node":"public","typeName":"Int","property":"baseIterations","value":"1000000"}
{"_id":{"$oid":"5c725951f7797b8298f07e6b"},"node":"public","typeName":"Float","property":"baseIterationsCoefficient","value":"1.0"}
{"_id":{"$oid":"5c725951f7797b8298f07e74"},"node":"public","typeName":"Int","property":"priorityClient","value":"1"}
{"_id":{"$oid":"5c725951f7797b8298f07e7c"},"node":"public","typeName":"Int","property":"priorityEmployees","value":"2"}
{"_id":{"$oid":"5c725951f7797b8298f07e84"},"node":"public","typeName":"Int","property":"priorityPurchasing","value":"4"}
{"_id":{"$oid":"5c725951f7797b8298f07e8a"},"node":"public","typeName":"Int","property":"priorityProduction","value":"8"}
{"_id":{"$oid":"5c725951f7797b8298f07e8e"},"node":"public","typeName":"Int","property":"priorityPublic","value":"2"}
{"_id":{"$oid":"5c725951f7797b8298f07e92"},"node":"public","typeName":"Boolean","property":"mongoTransferRecords","value":"true"}
{"_id":{"$oid":"5c725951f7797b8298f07e96"},"node":"public","typeName":"Boolean","property":"doWarmup","value":"true"}
{"_id":{"$oid":"5c725951f7797b8298f07e98"},"node":"public","typeName":"Boolean","property":"dbBackpressure","value":"true"}
{"_id":{"$oid":"5c725951f7797b8298f07e9a"},"node":"public","typeName":"Boolean","property":"debugMode","value":"false"}
{"_id":{"$oid":"5c725951f7797b8298f07e9c"},"node":"public","typeName":"Int","property":"groundIterations","value":"1000000"}
{"_id":{"$oid":"5c725951f7797b8298f07e9e"},"node":"public","typeName":"Int","property":"cores","value":"2"}
{"_id":{"$oid":"5c725951f7797b8298f07ea0"},"node":"public","typeName":"Long","property":"memory","value":"3817865216"}
{"_id":{"$oid":"5c725951f7797b8298f07ea2"},"node":"public","typeName":"Int","property":"latencyRecordingInterval","value":"1000"}
{"_id":{"$oid":"5c725951f7797b8298f07ea4"},"node":"public","typeName":"Int","property":"performanceRecordingIntervalMs","value":"100"}
{"_id":{"$oid":"5c725951f7797b8298f07ea6"},"node":"public","typeName":"Int","property":"throughputRecordingIntervalMs","value":"100"}
{"_id":{"$oid":"5c725951f7797b8298f07ea8"},"node":"public","typeName":"Long","property":"waitForBeingColdTimeoutMs","value":"30000"}
{"_id":{"$oid":"5c725951f7797b8298f07eaa"},"node":"public","typeName":"Long","property":"waitForBeingColdIntervalMs","value":"5000"}
{"_id":{"$oid":"5c725951f7797b8298f07eac"},"node":"public","typeName":"Boolean","property":"skipExecution","value":"false"}
{"_id":{"$oid":"5c725951f7797b8298f07eae"},"node":"public","typeName":"Boolean","property":"invokeBeforeAllAndAfterAllEvenIfNoTestsAreExpected","value":"false"}
